MANIFEST.in
README.txt
plonetheme.simplicity-configure.zcml
setup.py
plonetheme/__init__.py
plonetheme.simplicity.egg-info/PKG-INFO
plonetheme.simplicity.egg-info/SOURCES.txt
plonetheme.simplicity.egg-info/dependency_links.txt
plonetheme.simplicity.egg-info/entry_points.txt
plonetheme.simplicity.egg-info/namespace_packages.txt
plonetheme.simplicity.egg-info/not-zip-safe
plonetheme.simplicity.egg-info/paster_plugins.txt
plonetheme.simplicity.egg-info/requires.txt
plonetheme.simplicity.egg-info/top_level.txt
plonetheme/simplicity/__init__.py
plonetheme/simplicity/configure.zcml
plonetheme/simplicity/profiles.zcml
plonetheme/simplicity/setuphandlers.py
plonetheme/simplicity/skins.zcml
plonetheme/simplicity/tests.py
plonetheme/simplicity/version.txt
plonetheme/simplicity/browser/__init__.py
plonetheme/simplicity/browser/configure.zcml
plonetheme/simplicity/browser/interfaces.py
plonetheme/simplicity/browser/viewlet.pt
plonetheme/simplicity/browser/viewlets.py
plonetheme/simplicity/browser/images/README.txt
plonetheme/simplicity/browser/stylesheets/README.txt
plonetheme/simplicity/browser/stylesheets/main.css
plonetheme/simplicity/browser/templates/splash_image.pt
plonetheme/simplicity/profiles/default/cssregistry.xml
plonetheme/simplicity/profiles/default/import_steps.xml
plonetheme/simplicity/profiles/default/jsregistry.xml
plonetheme/simplicity/profiles/default/metadata.xml
plonetheme/simplicity/profiles/default/plonetheme.simplicity_various.txt
plonetheme/simplicity/profiles/default/skins.xml
plonetheme/simplicity/profiles/default/viewlets.xml
plonetheme/simplicity/skins/plonetheme_simplicity_custom_images/CONTENT.txt
plonetheme/simplicity/skins/plonetheme_simplicity_custom_images/Thumbs.db
plonetheme/simplicity/skins/plonetheme_simplicity_custom_images/banner.jpg
plonetheme/simplicity/skins/plonetheme_simplicity_custom_images/banner.jpg.metadata
plonetheme/simplicity/skins/plonetheme_simplicity_custom_images/mail_icon.gif
plonetheme/simplicity/skins/plonetheme_simplicity_custom_images/print_icon.gif
plonetheme/simplicity/skins/plonetheme_simplicity_custom_templates/CONTENT.txt
plonetheme/simplicity/skins/plonetheme_simplicity_custom_templates/column-tidier.js
plonetheme/simplicity/skins/plonetheme_simplicity_custom_templates/hide_columns.js
plonetheme/simplicity/skins/plonetheme_simplicity_custom_templates/main_template.pt
